lsdtt_xtensor_python.cpython-37m-darwin.so
lsdtt_xtensor_python-0.0.4.7.data/data/LICENSE
lsdtt_xtensor_python-0.0.4.7.dist-info/LICENSE
lsdtt_xtensor_python-0.0.4.7.dist-info/METADATA
lsdtt_xtensor_python-0.0.4.7.dist-info/WHEEL
lsdtt_xtensor_python-0.0.4.7.dist-info/top_level.txt
lsdtt_xtensor_python-0.0.4.7.dist-info/RECORD
