Metadata-Version: 2.1
Name: lsdtt-xtensor-python
Version: 0.0.4.7
Summary: This is an attempt to port LSDTT to Python
Home-page: https://lsdtopotools.github.io
Author: LSDTopoTools team -  Boris Gailleton
Author-email: boris.gailleton@gfz-potsdam.de
License: GNU General Public License v3
Keywords: lsdtt_xtensor_python
Platform: UNKNOWN
Requires-Dist: pybind11 (>=2.0.1)
Requires-Dist: numpy
